{
    "package": "ColdStart",
    "info": {
        "title": "Cold Start",
        "author": "etonedemid",
        "category": "game",
        "version": "3.2.0",
        "url": "https://github.com/etonedemid/cold-start-nx",
        "license": "GPLv3",
        "description": "Topdown roguelike on five platforms",
        "details": "roguelike survival with bombs, upgrades, parrying and a console where you can spawn a car and run enemies over. Runs on PC, Nintendo Switch and Wii U homebrew, and Android."
    },
    "assets": [
        {
            "type": "icon",
            "url": "icon.png"
        },
        {
            "type": "banner",
            "url": "screen.png"
        },
        {
            "url": "https://github.com/etonedemid/cold-start-nx/releases/download/v3.2.0/cold_start-wiiu-3.2.0.wuhb",
            "type": "update",
            "dest": "/wiiu/apps/ColdStart/cold_start-wiiu-3.2.0.wuhb"
        }
    ],
    "changelog": ""
}
